opensesame_plugins/audio_low_latency/__init__.py
opensesame_plugins/audio_low_latency/audio_low_latency_play/__init__.py
opensesame_plugins/audio_low_latency/audio_low_latency_play/audio_low_latency_play.png
opensesame_plugins/audio_low_latency/audio_low_latency_play/audio_low_latency_play.py
opensesame_plugins/audio_low_latency/audio_low_latency_play/audio_low_latency_play_large.png
opensesame_plugins/audio_low_latency/audio_low_latency_play_init/__init__.py
opensesame_plugins/audio_low_latency/audio_low_latency_play_init/audio_low_latency_play_init.png
opensesame_plugins/audio_low_latency/audio_low_latency_play_init/audio_low_latency_play_init.py
opensesame_plugins/audio_low_latency/audio_low_latency_play_init/audio_low_latency_play_init_large.png
opensesame_plugins/audio_low_latency/audio_low_latency_play_pause/__init__.py
opensesame_plugins/audio_low_latency/audio_low_latency_play_pause/audio_low_latency_play_pause.png
opensesame_plugins/audio_low_latency/audio_low_latency_play_pause/audio_low_latency_play_pause.py
opensesame_plugins/audio_low_latency/audio_low_latency_play_pause/audio_low_latency_play_pause_large.png
opensesame_plugins/audio_low_latency/audio_low_latency_play_resume/__init__.py
opensesame_plugins/audio_low_latency/audio_low_latency_play_resume/audio_low_latency_play_resume.png
opensesame_plugins/audio_low_latency/audio_low_latency_play_resume/audio_low_latency_play_resume.py
opensesame_plugins/audio_low_latency/audio_low_latency_play_resume/audio_low_latency_play_resume_large.png
opensesame_plugins/audio_low_latency/audio_low_latency_play_start/__init__.py
opensesame_plugins/audio_low_latency/audio_low_latency_play_start/audio_low_latency_play_start.png
opensesame_plugins/audio_low_latency/audio_low_latency_play_start/audio_low_latency_play_start.py
opensesame_plugins/audio_low_latency/audio_low_latency_play_start/audio_low_latency_play_start_large.png
opensesame_plugins/audio_low_latency/audio_low_latency_play_stop/__init__.py
opensesame_plugin_audio_low_latency-10.9.1.dist-info/COPYING
opensesame_plugin_audio_low_latency-10.9.1.dist-info/LICENSE.md
opensesame_plugin_audio_low_latency-10.9.1.dist-info/METADATA
opensesame_plugin_audio_low_latency-10.9.1.dist-info/WHEEL
opensesame_plugin_audio_low_latency-10.9.1.dist-info/RECORD
