Metadata-Version: 2.3
Name: opensesame-plugin-audio_low_latency
Version: 10.9.1
Summary: An OpenSesame Plug-in for playing and recording audio files with low latency on Linux
License: LICENSE.md
Author: Bob Rosbag
Author-email: debian@bobrosbag.nl
Requires-Python: >=3.7
Classifier: License :: Other/Proprietary License
Classifier: Programming Language :: Python :: 3
Classifier: Programming Language :: Python :: 3.7
Classifier: Programming Language :: Python :: 3.8
Classifier: Programming Language :: Python :: 3.9
Classifier: Programming Language :: Python :: 3.10
Classifier: Programming Language :: Python :: 3.11
Classifier: Programming Language :: Python :: 3.12
Classifier: Programming Language :: Python :: 3.13
Requires-Dist: numpy
Requires-Dist: pyalsaaudio (>=0.8.4) ; sys_platform == "linux"
Requires-Dist: pyaudio
Requires-Dist: pygame (>=2.0.0)
Requires-Dist: sounddevice
Project-URL: Homepage, https://github.com/dev-jam/opensesame-plugin-audio_low_latency
Project-URL: Repository, https://github.com/dev-jam/opensesame-plugin-audio_low_latency
